bumpver/__init__.py
bumpver/__main__.py
bumpver/cli.py
bumpver/config.py
bumpver/hooks.py
bumpver/parse.py
bumpver/pathlib.py
bumpver/patterns.py
bumpver/pysix.py
bumpver/regexfmt.py
bumpver/rewrite.py
bumpver/setuptools_v65_version.py
bumpver/utils.py
bumpver/v1patterns.py
bumpver/v1rewrite.py
bumpver/v1version.py
bumpver/v2patterns.py
bumpver/v2rewrite.py
bumpver/v2version.py
bumpver/vcs.py
bumpver/version.py
bumpver-2025.1131.dist-info/LICENSE
bumpver-2025.1131.dist-info/METADATA
bumpver-2025.1131.dist-info/WHEEL
bumpver-2025.1131.dist-info/entry_points.txt
bumpver-2025.1131.dist-info/top_level.txt
bumpver-2025.1131.dist-info/zip-safe
bumpver-2025.1131.dist-info/RECORD
