Metadata-Version: 2.1
Name: bumpver
Version: 2025.1131
Summary: Bump version numbers in project files.
Home-page: https://github.com/mbarkhau/bumpver
Author: Manuel Barkhau
Author-email: mbarkhau@gmail.com
License: MIT
Keywords: version bumpver calver semver versioning bumpversion pep440
Classifier: Development Status :: 4 - Beta
Classifier: Environment :: Console
Classifier: Environment :: Other Environment
Classifier: Intended Audience :: Developers
Classifier: License :: OSI Approved :: MIT License
Classifier: Operating System :: Unix
Classifier: Operating System :: POSIX
Classifier: Operating System :: Microsoft :: Windows
Classifier: Operating System :: MacOS :: MacOS X
Classifier: Programming Language :: Python
Classifier: Programming Language :: Python :: 2.7
Classifier: Programming Language :: Python :: 3
Classifier: Programming Language :: Python :: Implementation :: CPython
Classifier: Programming Language :: Python :: Implementation :: PyPy
Classifier: Topic :: Software Development :: Libraries
Classifier: Topic :: Software Development :: Libraries :: Python Modules
Requires-Python: >=2.7
License-File: LICENSE
Requires-Dist: toml
Requires-Dist: lexid
Requires-Dist: colorama (>=0.4)
Requires-Dist: pathlib2 ; python_version < "3.4"
Requires-Dist: enum34 ; python_version < "3.4"
Requires-Dist: typing ; python_version < "3.5"
Requires-Dist: click (<8.0) ; python_version < "3.6"
Requires-Dist: click ; python_version >= "3.6"
